datacrux/__init__.py
datacrux/datacrux.py
datacrux-0.0.1.dist-info/LICENSE
datacrux-0.0.1.dist-info/METADATA
datacrux-0.0.1.dist-info/WHEEL
datacrux-0.0.1.dist-info/top_level.txt
datacrux-0.0.1.dist-info/RECORD
